synbiopython/__init__.py
synbiopython/version.py
synbiopython/codon/__init__.py
synbiopython/codon/table.py
synbiopython/codon/taxonomy_utils.py
synbiopython/codon/utils.py
synbiopython/codon/data/37762.txt
synbiopython/codon/data/45372.txt
synbiopython/codon/data/9606.txt
synbiopython/codon/data/species.table
synbiopython/genbabel/__init__.py
synbiopython/genbabel/utilities.py
synbiopython/genbabel/gensbolconv/GenSBOLconv.py
synbiopython/genbabel/gensbolconv/__init__.py
synbiopython/genbabel/sbmlgen/SBMLgen.py
synbiopython/genbabel/sbmlgen/__init__.py
synbiopython/genbabel/sbmlgen/simplesbml.py
synbiopython/genbabel/sedmlomexgen/SEDMLOMEXgen.py
synbiopython/genbabel/sedmlomexgen/__init__.py
synbiopython/genbabel/simplednaplot/SimpleDNAplot.py
synbiopython/genbabel/simplednaplot/__init__.py
synbiopython/lab_automation/__init__.py
synbiopython/lab_automation/tools.py
synbiopython/lab_automation/containers/Plate.py
synbiopython/lab_automation/containers/Well.py
synbiopython/lab_automation/containers/WellContent.py
synbiopython/lab_automation/containers/__init__.py
synbiopython/lab_automation/containers/builtin_containers.py
synbiopython/lab_automation/containers/helper_functions.py
synbiopython/lab_automation/picklist/PickList.py
synbiopython/lab_automation/picklist/Transfer.py
synbiopython/lab_automation/picklist/__init__.py
synbiopython-0.2.0.dist-info/LICENSE
synbiopython-0.2.0.dist-info/METADATA
synbiopython-0.2.0.dist-info/WHEEL
synbiopython-0.2.0.dist-info/top_level.txt
synbiopython-0.2.0.dist-info/RECORD
