Metadata-Version: 2.1
Name: synbiopython
Version: 0.2.0
Summary: Python tools for Synthetic Biology.
Home-page: https://synbiopython.org
Author: Global Biofoundries Alliance
License: UNKNOWN
Platform: UNKNOWN
Classifier: Programming Language :: Python :: 3
Classifier: License :: OSI Approved :: MIT License
Classifier: Operating System :: OS Independent
Requires-Python: >=3.6
Requires-Dist: pandas (>=0.22)
Requires-Dist: numpy
Requires-Dist: dnaplotlib
Requires-Dist: biopython
Requires-Dist: reportlab
Requires-Dist: tesbml
Requires-Dist: nbgitpuller
Requires-Dist: tellurium
